{"compressionlevel":-1,"height":13,"infinite":false,"layers":[{"id":39,"layers":[{"data":[0,0,0,0,0,0,0,0,0,0,0,0,0,0,0,0,0,0,0,0,0,0,0,0,0,0,0,0,0,0,0,0,0,0,0,0,0,0,0,0,0,0,0,0,0,0,0,0,0,0,0,0,0,0,0,0,0,0,0,0,0,0,0,0,0,0,0,0,0,0,0,0,0,0,0,0,0,0,0,0,0,0,0,0,0,0,0,0,0,0,0,0,0,0,0,0,0,0,0,0,0,0,0,0,0,0,0,0,0,0,0,0,0,0,0,0,0,0,0,0,0,0,0,0,0,0,0,0,0,0,0,0,0,0,0,0,0,0,0,0,0,0,0,0,0,0,0,0,0,0,0,0,0,0,0,0,0,0,0,0,0,0,0,0,0,0,0,0,0,0,0,0,0,0,0,0,0,0,0,0,0,0,0,0,0,0,0,0,0,0,0,0,0,0,0,0,0,0,0,0,0,0,0,0,2,2,2,2,2,0,0,0,0,0,0,0,0,0,0,0,0,0,0,0,0,2,2,2,2,2,0,0,0,0,0,0,0,0,0,0,0,0,0,0,0,0,2,2,2,2,2,0,0,0,0,0,0,0,0,0,0,0,0,0,0,0,0,0,0,0,0,0,0],"height":13,"id":6,"name":"start","opacity":1,"type":"tilelayer","visible":true,"width":21,"x":0,"y":0},{"id":77,"layers":[],"name":"Others","opacity":1,"type":"group","visible":true,"x":0,"y":0},{"id":72,"layers":[{"data":[0,0,0,0,0,0,0,0,0,0,0,0,0,0,0,0,0,0,0,0,0,0,0,0,0,0,0,0,0,0,0,0,0,0,0,0,0,0,0,0,0,0,0,0,0,0,0,0,0,0,0,0,0,0,0,0,0,0,0,0,0,0,0,0,0,0,0,0,0,0,0,0,0,0,0,0,0,0,0,0,0,0,0,0,0,0,0,0,0,0,0,0,0,0,0,0,0,0,0,0,0,0,0,0,0,0,0,0,0,0,0,0,0,0,0,0,0,0,0,0,0,0,0,0,0,0,0,0,0,0,0,0,0,0,0,0,0,0,0,0,0,0,0,0,0,0,0,0,0,0,0,0,0,0,0,0,0,0,0,0,0,0,0,0,0,0,0,0,0,0,0,0,0,0,0,0,0,0,0,0,0,0,0,0,0,0,0,0,0,0,0,0,0,0,0,0,0,0,0,0,0,0,0,0,0,0,0,0,0,0,0,0,0,0,0,0,0,0,0,0,0,0,0,0,0,0,0,0,0,0,0,0,9,9,9,9,0,0,0,0,0,0,0,0,0,0,0,0,0,0,0,0,0,9,9,9,9,0,0,0,0,0,0,0,0,0,0,0,0,0,0,0,0],"height":13,"id":94,"name":"exitLand","opacity":1,"properties":[{"name":"exitUrl","type":"string","value":"land.json#entranceFromBeach"}],"type":"tilelayer","visible":true,"width":21,"x":0,"y":0}],"name":"Exits","opacity":1,"type":"group","visible":true,"x":0,"y":0},{"id":73,"layers":[],"name":"Entries","opacity":1,"type":"group","visible":true,"x":0,"y":0},{"id":79,"layers":[{"data":[0,0,0,0,0,0,0,0,0,0,0,0,0,0,0,0,0,0,0,0,0,0,0,0,0,0,0,0,0,0,0,0,0,0,0,0,0,0,0,0,0,0,0,0,0,0,0,0,0,0,0,0,0,0,0,0,0,0,0,0,0,0,0,0,0,0,0,0,0,0,0,0,0,0,0,0,0,0,0,0,0,0,0,0,0,0,0,0,0,0,0,0,0,0,0,0,0,0,0,0,0,0,0,0,0,0,0,0,0,0,0,0,0,0,0,0,0,0,0,0,0,0,0,0,0,0,0,0,0,0,0,0,0,0,0,0,0,0,0,0,0,0,0,0,0,0,0,0,0,0,0,0,0,0,0,0,0,0,0,0,0,0,0,0,0,0,0,0,0,0,0,0,0,0,0,0,0,0,0,0,0,0,0,0,0,0,0,0,0,0,0,0,0,0,0,0,0,0,0,0,0,0,0,0,0,0,0,0,0,0,0,0,0,0,0,0,0,0,0,0,0,0,0,0,0,0,0,0,0,0,0,0,0,0,0,0,0,0,0,0,0,0,0,0,0,0,0,0,0,0,0,0,0,0,0,0,0,0,0,0,0,0,0,0,0,0,0,0,0,0,0,0,0],"height":13,"id":78,"name":"jitsiAccueil","opacity":1,"properties":[{"name":"jitsiRoom","type":"string","value":"jitsi"},{"name":"jitsiTrigger","type":"string","value":"onaction"}],"type":"tilelayer","visible":true,"width":21,"x":0,"y":0},{"data":[0,0,0,0,0,0,0,0,0,0,0,0,0,0,0,0,0,0,0,0,0,0,0,0,0,0,0,0,0,0,0,0,0,0,0,0,0,0,0,0,0,0,0,0,0,0,0,0,0,0,0,0,0,0,0,0,0,0,0,0,0,0,0,0,0,0,0,0,12,12,12,12,12,12,0,0,0,0,0,0,0,0,0,0,0,0,0,0,0,12,12,12,12,12,12,0,0,0,0,0,0,0,0,0,0,0,0,0,0,0,12,12,12,12,12,12,0,0,0,0,0,0,0,0,0,0,0,0,0,0,0,12,12,12,12,12,12,0,0,0,0,0,0,0,0,0,0,0,0,0,0,0,12,12,12,12,12,12,0,0,0,0,0,0,0,0,0,0,0,0,0,0,0,0,0,0,0,0,0,0,0,0,0,0,0,0,0,0,0,0,0,0,0,0,0,0,0,0,0,0,0,0,0,0,0,0,0,0,0,0,0,0,0,0,0,0,0,0,0,0,0,0,0,0,0,0,0,0,0,0,0,0,0,0,0,0,0,0,0,0,0,0,0,0,0,0,0,0,0,0,0,0,0,0,0,0,0,0,0,0,0,0,0,0,0,0,0,0,0,0,0,0,0],"height":13,"id":86,"name":"jitsiSecret2","opacity":1,"properties":[{"name":"jitsiInterfaceConfig","type":"string","value":"{ \"DEFAULT_BACKGROUND\": \"#87643c\" }"},{"name":"jitsiRoom","type":"string","value":"jitsiSecret2"},{"name":"jitsiRoomAdminTag","type":"string","value":"admin"},{"name":"jitsiTrigger","type":"string","value":"onaction"}],"type":"tilelayer","visible":true,"width":21,"x":0,"y":0},{"data":[0,0,0,0,0,0,0,0,0,0,0,0,0,0,0,0,0,0,0,0,0,0,0,0,0,0,0,0,0,0,0,0,0,0,0,0,0,0,0,0,0,0,0,0,0,0,0,0,0,0,0,0,0,0,0,0,0,0,0,0,0,0,0,0,0,0,0,0,0,0,0,0,0,0,0,12,12,12,12,12,12,12,0,0,0,0,0,0,0,0,0,0,0,0,0,0,12,12,12,12,12,12,12,0,0,0,0,0,0,0,0,0,0,0,0,0,0,12,12,12,12,12,12,12,0,0,0,0,0,0,0,0,0,0,0,0,0,0,12,12,12,12,12,12,12,0,0,0,0,0,0,0,0,0,0,0,0,0,0,12,12,12,12,12,12,12,0,0,0,0,0,0,0,0,0,0,0,0,0,0,12,12,12,12,12,12,12,0,0,0,0,0,0,0,0,0,0,0,0,0,0,0,0,0,0,0,0,0,0,0,0,0,0,0,0,0,0,0,0,0,0,0,0,0,0,0,0,0,0,0,0,0,0,0,0,0,0,0,0,0,0,0,0,0,0,0,0,0,0,0,0,0,0,0,0,0,0,0,0,0,0,0,0,0,0,0,0,0,0,0,0,0,0],"height":13,"id":87,"name":"jitsiSecret1","opacity":1,"properties":[{"name":"jitsiRoom","type":"string","value":"jitsiSecret1"},{"name":"jitsiTrigger","type":"string","value":"onaction"}],"type":"tilelayer","visible":true,"width":21,"x":0,"y":0}],"name":"Jitsi","opacity":1,"type":"group","visible":true,"x":0,"y":0},{"id":81,"layers":[{"data":[0,0,0,0,0,0,0,0,0,0,0,0,0,0,0,0,0,0,0,0,0,0,0,0,0,0,0,0,0,0,0,0,0,0,0,0,0,0,0,0,0,0,0,0,0,0,0,0,0,0,0,0,0,0,0,0,0,0,0,0,0,0,0,0,0,0,0,0,0,0,0,0,0,0,0,0,0,0,0,0,0,0,0,0,0,0,0,0,0,0,0,0,0,0,0,0,0,0,0,0,0,0,0,0,0,0,0,0,0,0,0,0,0,0,0,0,0,0,0,0,0,0,0,0,0,0,0,0,0,0,0,0,0,0,0,0,0,0,0,0,0,0,0,0,0,0,0,0,0,0,0,0,0,0,0,0,0,0,0,0,0,0,0,0,0,0,0,0,0,0,0,0,0,0,0,0,0,0,0,0,0,0,0,0,0,0,0,0,0,0,0,0,0,0,0,0,0,0,0,0,0,0,0,0,0,0,0,0,0,0,0,0,0,0,0,0,0,0,0,0,0,0,0,0,0,0,0,0,0,0,0,0,0,0,0,0,0,0,0,0,0,0,0,0,0,0,0,0,0,0,0,0,0,0,0,0,0,0,0,0,0,0,0,0,0,0,0,0,0,0,0,0,0],"height":13,"id":80,"name":"urlScribbl","opacity":1,"properties":[{"name":"openWebsite","type":"string","value":"https://garticphone.com/fr"},{"name":"openWebsitePolicy","type":"string","value":"fullscreen"},{"name":"openWebsiteWidth","type":"int","value":50}],"type":"tilelayer","visible":true,"width":21,"x":0,"y":0},{"data":[0,0,0,0,0,0,0,0,0,0,0,0,0,0,0,0,0,0,0,0,0,0,0,0,0,0,0,0,0,0,0,0,0,0,0,0,0,0,0,0,0,0,0,0,0,0,0,0,0,0,0,0,0,0,0,0,0,0,0,0,0,0,0,0,0,0,0,0,0,0,0,0,0,0,0,0,0,0,0,0,0,0,0,0,0,0,0,0,0,0,0,0,0,0,0,0,0,0,0,0,0,0,0,0,0,0,0,0,0,0,0,0,0,0,0,0,0,0,0,0,0,0,0,0,0,0,0,0,0,0,0,0,0,0,0,0,0,0,0,0,0,0,0,0,0,0,0,0,0,0,0,0,0,0,0,0,0,0,0,0,0,0,0,0,0,0,0,0,0,0,0,0,0,0,0,0,0,0,0,0,0,0,0,0,0,0,0,0,0,0,0,0,0,0,0,0,0,0,0,0,0,0,0,0,0,0,0,0,0,0,0,0,0,0,0,0,0,0,0,0,0,0,0,0,0,0,0,0,0,0,0,0,0,0,0,0,0,0,0,0,0,0,0,0,0,0,0,0,0,0,0,0,0,0,0,0,0,0,0,0,0,0,0,0,0,0,0,0,0,0,0,0,0],"height":13,"id":83,"name":"urlUNO","opacity":1,"properties":[{"name":"openWebsite","type":"string","value":"https://garticphone.com/fr"},{"name":"openWebsitePolicy","type":"string","value":"fullscreen"},{"name":"openWebsiteWidth","type":"int","value":50}],"type":"tilelayer","visible":true,"width":21,"x":0,"y":0},{"data":[0,0,0,0,0,0,0,0,0,0,0,0,0,0,0,0,0,0,0,0,0,0,0,0,0,0,0,0,0,0,0,0,0,0,0,0,0,0,0,0,0,0,0,0,0,0,0,0,0,0,0,0,0,0,0,0,0,0,0,0,0,0,0,0,0,0,0,0,0,0,0,0,0,0,0,0,0,0,0,0,0,0,0,0,0,0,0,0,0,0,0,0,0,0,0,0,0,0,0,0,0,0,0,0,0,0,0,0,0,0,0,0,0,0,0,0,0,0,0,0,0,0,0,0,0,0,0,0,0,0,0,0,0,0,0,0,0,0,0,0,0,0,0,0,0,0,0,0,0,0,0,0,0,0,0,0,0,0,0,0,0,0,0,0,0,0,0,0,0,0,0,0,0,0,0,0,0,0,0,0,0,0,0,0,0,0,0,0,0,0,0,0,0,0,0,0,0,0,0,0,0,0,0,0,0,0,0,0,0,0,0,0,0,0,0,0,0,0,0,0,0,0,0,0,0,0,0,0,0,0,0,0,0,0,0,0,0,0,0,0,0,0,0,0,0,0,0,0,0,0,0,0,0,0,0,0,0,0,0,0,0,0,0,0,0,0,0,0,0,0,0,0,0],"height":13,"id":84,"name":"urlGartic","opacity":1,"properties":[{"name":"openWebsite","type":"string","value":"https://garticphone.com/fr"},{"name":"openWebsitePolicy","type":"string","value":"fullscreen"},{"name":"openWebsiteWidth","type":"int","value":50}],"type":"tilelayer","visible":true,"width":21,"x":0,"y":0},{"data":[0,0,0,0,0,0,0,0,0,0,0,0,0,0,0,0,0,0,0,0,0,0,0,0,0,0,0,0,0,0,0,0,0,0,0,0,0,0,0,0,0,0,0,0,0,0,0,0,0,0,0,0,0,0,0,0,0,0,0,0,0,0,0,0,0,0,0,0,0,0,0,0,0,0,0,0,0,0,0,0,0,0,0,0,0,0,0,0,0,0,0,0,0,0,0,0,0,0,0,0,0,0,0,0,0,0,0,0,0,0,0,0,0,0,0,0,0,0,0,0,0,0,0,0,0,0,0,0,0,0,0,0,0,0,0,0,0,0,0,0,0,0,0,0,0,0,0,0,0,0,0,0,0,0,0,0,0,0,0,0,0,0,0,0,0,0,0,0,0,0,0,0,0,0,0,0,0,0,0,0,0,0,0,0,0,0,0,0,0,0,0,0,0,0,0,0,0,0,0,0,0,0,0,0,0,0,0,0,0,0,0,0,0,0,0,0,0,0,0,0,0,0,0,0,0,0,0,0,0,0,0,0,0,0,0,0,0,0,0,0,0,0,0,0,0,0,0,0,0,0,0,0,0,0,0,0,0,0,0,0,0,0,0,0,0,0,0,0,0,0,0,0,0],"height":13,"id":85,"name":"urlNaval","opacity":1,"properties":[{"name":"openWebsite","type":"string","value":"https://garticphone.com/fr"},{"name":"openWebsitePolicy","type":"string","value":"fullscreen"},{"name":"openWebsiteWidth","type":"int","value":50}],"type":"tilelayer","visible":true,"width":21,"x":0,"y":0}],"name":"URLs","opacity":1,"type":"group","visible":true,"x":0,"y":0},{"data":[0,0,0,0,0,0,0,0,0,0,0,0,0,0,0,0,0,0,0,0,0,0,0,0,0,0,0,0,0,0,0,0,0,0,0,0,0,0,0,0,0,0,0,0,0,0,0,0,0,0,0,0,0,0,0,0,0,0,0,0,0,0,0,0,0,0,0,0,0,0,0,0,0,0,0,0,0,0,0,0,0,0,0,0,0,0,0,0,0,0,0,0,0,0,0,0,0,0,0,0,0,0,0,0,0,0,0,0,0,0,0,0,0,0,0,0,0,0,0,0,0,0,0,0,0,0,0,0,0,0,0,0,0,0,0,0,0,0,0,0,0,0,0,0,0,0,0,0,0,0,0,0,0,0,0,0,0,0,0,0,0,0,0,0,0,0,0,0,0,0,0,0,0,0,0,0,0,0,0,0,0,0,0,0,0,0,0,0,0,0,0,0,0,0,0,0,0,0,0,0,0,0,0,0,0,0,0,0,0,0,0,0,0,0,0,0,0,0,0,0,0,0,0,0,0,0,0,0,0,0,0,0,0,0,0,0,0,0,0,0,0,0,0,0,0,0,0,0,0,0,0,0,0,0,0,0,0,0,0,0,0,0,0,0,0,0,0,0,0,0,0,0,0],"height":13,"id":75,"name":"_SILENTS","opacity":1,"properties":[{"name":"silent","type":"bool","value":true}],"type":"tilelayer","visible":true,"width":21,"x":0,"y":0},{"data":[0,0,0,0,0,0,0,0,0,0,0,0,0,0,0,0,0,0,0,0,0,0,0,0,0,0,0,0,0,0,0,0,0,0,0,0,0,0,0,0,0,0,1,1,1,1,1,1,1,1,1,1,1,1,1,1,1,1,1,1,1,1,1,1,1,1,0,0,0,0,0,0,1,0,0,0,0,0,0,0,0,0,0,0,1,1,1,0,0,0,0,0,0,0,0,0,0,0,0,0,0,0,0,0,0,1,1,1,0,0,1,0,1,1,0,0,0,0,0,1,1,1,0,0,0,0,1,0,0,0,0,1,0,1,1,0,0,0,0,0,1,1,1,0,0,0,0,1,0,0,0,0,0,0,0,0,0,0,0,0,0,0,0,0,0,0,0,0,0,0,0,0,0,0,0,0,0,0,0,0,0,0,0,0,0,0,0,0,0,0,0,0,0,0,0,0,0,0,0,0,0,0,0,0,0,0,0,0,0,0,0,0,0,0,0,0,0,0,0,0,0,0,0,0,0,0,0,0,0,0,0,0,0,0,0,0,0,0,0,0,0,0,0,0,0,0,0,0,0,0,0,0,0,0,0,0,0,0,0,0,0,0,0,0,0,0,0,0,0,0,0,0,0],"height":13,"id":7,"name":"_COLLIDES","opacity":1,"type":"tilelayer","visible":true,"width":21,"x":0,"y":0}],"name":"Settings","opacity":1,"type":"group","visible":true,"x":0,"y":0},{"id":47,"layers":[{"data":[21100,21098,21099,21100,21098,21099,21098,21099,21100,21098,21099,21100,21098,21099,21100,21098,21099,21098,21099,21100,21098,21100,21098,21099,21100,21098,21099,21098,21099,21100,21098,21099,21100,21098,21099,21100,21098,21099,21098,21099,21100,21098,21099,21100,21098,21099,21100,21098,21100,21098,21099,21100,21098,21099,21100,21098,21099,21100,21098,21100,21098,21099,21100,21100,21098,21099,21100,21098,21099,21098,21099,21100,21098,21099,21100,21098,21099,21100,21098,21099,21098,21099,21100,21098,21100,21098,21099,21100,21098,21099,21098,21099,21100,21098,21099,21100,21098,21099,21100,21098,21099,21098,21099,21100,21098,21099,21100,21098,21099,21100,21098,21100,21098,21099,21100,21098,21099,21100,21098,21099,21100,21098,21100,21098,21099,21100,21100,21098,21099,21100,21098,21099,21098,21099,21100,21098,21099,21100,21098,21099,21100,21098,21099,21098,21099,21100,21098,21100,21098,21099,21100,21098,21099,21098,21099,21100,21098,21099,21100,21098,21099,21100,21098,21099,21098,21099,21100,21098,21099,21100,21098,21099,21100,21098,21100,21098,21099,21100,21098,21099,21100,21098,21099,21100,21098,21100,21098,21099,21100,21100,21098,21099,21100,21098,21099,21098,21099,21100,21098,21099,21100,21098,21099,21100,21098,21099,21098,21099,21100,21098,21099,21100,21098,21099,21100,21098,21100,21098,21099,21100,21098,21099,21100,21098,21099,21100,21098,21100,21098,21099,21100,21099,21100,21098,21099,21100,21098,21099,21100,21098,21099,21100,21098,21099,21100,21098,21099,21100,21100,21098,21099,21100,21099,21100,21098,21099,21100,21098,21099,21100,21098,21099,21100,21098,21099,21100,21098,21099,21100,21100,21098,21099,21100],"height":13,"id":41,"name":"Floor","opacity":1,"type":"tilelayer","visible":true,"width":21,"x":0,"y":0},{"data":[0,0,0,0,0,0,0,0,0,0,0,0,0,0,0,0,0,0,0,0,0,0,0,0,0,0,0,0,0,0,0,0,0,0,0,0,0,0,0,0,0,0,0,0,0,0,0,0,0,0,0,0,0,0,0,0,0,0,0,0,0,0,0,0,0,0,0,0,0,0,0,0,0,0,0,0,0,0,0,0,0,0,0,0,0,0,0,0,0,0,0,0,0,0,0,0,0,0,0,0,0,0,0,0,0,0,0,0,0,0,0,0,0,0,0,0,0,0,0,0,0,0,0,0,0,0,0,0,0,0,0,0,0,0,0,0,0,0,0,0,0,0,0,0,0,0,0,0,0,0,0,0,0,0,0,0,0,0,0,0,0,0,0,0,0,0,0,0,0,0,0,0,0,0,0,0,0,0,0,0,0,0,0,0,0,0,0,0,0,0,0,0,0,0,0,0,0,0,0,0,0,0,0,0,0,0,0,0,0,0,0,0,0,0,0,0,0,0,0,0,0,0,0,0,0,0,0,0,0,0,0,0,0,0,0,0,0,0,0,0,0,0,0,0,0,0,0,0,0,0,0,0,0,0,0,0,0,0,0,0,0,0,0,0,0,0,0,0,0,0,0,0,0],"height":13,"id":42,"name":"Floor 1","opacity":1,"type":"tilelayer","visible":true,"width":21,"x":0,"y":0},{"data":[2941,0,2941,2941,2941,2941,2941,2941,2941,2941,2941,2941,2941,2941,2941,2941,2941,2941,2941,2941,2941,2941,0,2941,2941,2941,2941,2941,2941,2941,2941,2941,2941,2941,2941,2941,2941,2941,2941,2941,2941,2941,2941,0,2941,2941,2941,2941,2941,2941,2941,2941,2941,2941,2941,2941,2941,2941,2941,2941,2941,2941,2941,3021,2941,2941,2941,2941,2941,2941,2941,2941,2941,2941,2941,2941,2941,2941,2941,2941,2941,2941,2941,2941,3021,2941,2941,2941,2941,2941,2941,2941,2941,2941,2941,2941,2941,2941,2941,2941,2941,2941,2941,2941,2941,3021,2941,2941,2941,2941,2941,2941,2941,2941,2941,2941,2941,2941,2941,2941,2941,2941,2941,2941,2941,2941,3021,2941,2941,2941,2941,2941,2941,2941,2941,2941,2941,2941,2941,2941,2941,2941,2941,2941,2941,2941,2941,3021,2941,2941,2941,2941,2941,2941,2941,2941,2941,2941,2941,2941,2941,2941,2941,2941,2941,2941,2941,2941,3021,2941,2941,2941,2941,2941,2941,2941,2941,2941,2941,2941,2941,2941,2941,2941,2941,2941,2941,2941,2941,3021,2941,2941,2941,2941,2941,2941,2941,2941,2941,2941,2941,2941,2941,2941,2941,2941,2941,2941,2941,2941,3021,2941,2941,2941,2941,2941,2941,2941,2941,2941,2941,2941,2941,2941,2941,2941,2941,2941,2941,2941,2941,3021,2941,2941,2941,2941,2941,2941,2941,2941,2941,2941,2941,2941,2941,2941,2941,2941,2941,2941,2941,2941,3021,2941,2941,2941,2941,2941,2941,2941,2941,2941,2941,2941,2941,2941,2941,2941,2941,2941,2941,2941,2941],"height":13,"id":43,"name":"Floor 2","opacity":1,"type":"tilelayer","visible":true,"width":21,"x":0,"y":0},{"data":[0,0,0,0,0,0,0,0,0,0,0,0,0,0,0,0,0,0,0,0,0,0,0,0,0,0,0,0,0,0,0,0,0,0,0,0,0,0,0,0,0,0,0,0,0,0,0,0,0,0,0,0,0,0,0,0,0,0,0,0,0,0,0,0,0,0,0,0,0,4544,4545,4546,0,0,0,0,0,0,4544,4545,4546,0,0,0,0,0,0,0,0,0,4624,4625,4626,0,0,0,0,0,0,4624,4625,4626,0,0,0,0,0,0,0,0,0,0,0,0,0,0,0,0,0,0,0,0,0,0,0,0,0,0,0,0,0,0,0,0,0,0,0,0,0,0,0,0,0,0,0,0,0,0,0,0,0,0,0,0,0,0,0,0,0,0,0,0,0,0,0,0,0,0,0,0,0,0,0,0,0,0,0,0,0,0,0,0,0,0,0,0,0,0,0,0,0,0,0,0,0,0,0,0,0,0,0,0,0,0,0,0,0,0,0,0,0,0,0,0,0,0,0,0,0,0,0,0,0,0,0,0,0,0,0,0,0,0,0,0,0,0,0,0,0,0,0,0,0,0,0,0,0,0,0,0,0,0,0,0,0,0,0,0,0,0,0,0,0,0,0,0,0,0,0,0,0,0,0],"height":13,"id":44,"name":"Floor 3","opacity":1,"type":"tilelayer","visible":true,"width":21,"x":0,"y":0},{"data":[0,0,0,0,0,0,0,0,0,0,0,0,0,0,0,0,0,0,0,0,0,0,0,0,0,0,0,0,0,0,0,0,0,0,0,0,0,0,0,0,0,0,0,0,0,0,0,0,0,0,0,0,0,0,0,0,0,0,0,0,0,0,0,0,0,0,0,0,0,0,0,0,0,0,0,0,0,0,0,0,0,0,0,0,0,0,0,0,0,0,0,0,0,0,0,0,0,0,0,0,0,0,0,0,0,0,0,0,0,0,0,0,0,0,0,0,0,0,0,0,0,0,0,0,0,0,0,0,0,0,0,0,0,0,0,0,0,0,0,0,0,0,0,0,0,0,0,0,0,0,0,0,0,0,0,0,0,0,0,0,0,0,0,0,0,0,0,0,0,0,0,0,0,0,0,0,0,0,0,0,0,0,0,0,0,0,0,0,0,0,0,0,0,0,0,0,0,0,0,0,0,0,0,0,0,0,0,0,0,0,0,0,0,0,0,0,0,0,0,0,0,0,0,0,0,0,0,0,0,0,0,0,0,0,0,0,0,0,0,0,0,0,0,0,0,0,0,0,0,0,0,0,0,0,0,0,0,0,0,0,0,0,0,0,0,0,0,0,0,0,0,0,0],"height":13,"id":45,"name":"Floor 4","opacity":1,"type":"tilelayer","visible":true,"width":21,"x":0,"y":0},{"data":[0,0,0,0,0,0,0,0,0,0,0,0,0,0,0,0,0,0,0,0,0,0,0,0,0,0,0,0,0,0,0,0,0,0,0,0,0,0,0,0,0,0,0,0,0,0,0,0,0,0,0,0,0,0,0,0,0,0,0,0,0,0,0,0,0,0,0,0,0,0,0,0,0,0,0,0,0,0,0,0,0,0,0,0,0,0,0,0,0,0,0,0,0,0,0,0,0,0,0,0,0,0,0,0,0,0,0,0,0,0,0,0,0,0,0,0,0,0,0,0,0,0,0,0,0,0,0,0,0,0,0,0,0,0,0,0,0,0,0,0,0,0,0,0,0,0,0,0,0,0,0,0,0,0,0,0,0,0,0,0,0,0,0,0,0,0,0,0,0,0,0,0,0,0,0,0,0,0,0,0,0,0,0,0,0,0,0,0,0,0,0,0,0,0,0,0,0,0,0,0,0,0,0,0,0,0,0,0,0,0,0,0,0,0,0,0,0,0,0,0,0,0,0,0,0,0,0,0,0,0,0,0,0,0,0,0,0,0,0,0,0,0,0,0,0,0,0,0,0,0,0,0,0,0,0,0,0,0,0,0,0,0,0,0,0,0,0,0,0,0,0,0,0],"height":13,"id":46,"name":"Floor 5","opacity":1,"type":"tilelayer","visible":true,"width":21,"x":0,"y":0}],"name":"Floor","opacity":1,"type":"group","visible":true,"x":0,"y":0},{"id":54,"layers":[{"data":[0,0,0,0,0,0,0,0,0,0,0,0,0,0,0,0,0,0,0,0,0,0,0,0,0,0,0,0,0,0,0,0,0,0,0,0,0,0,0,0,0,0,0,0,0,0,0,0,0,0,0,0,0,0,0,0,0,0,0,0,0,0,0,0,0,0,0,0,0,0,0,0,0,0,0,0,0,0,0,0,0,0,0,0,0,0,0,0,0,0,0,0,0,0,0,0,0,0,0,0,0,0,0,0,0,0,0,0,0,0,0,0,0,0,0,0,0,0,0,0,0,0,0,0,0,0,0,0,0,0,0,0,0,0,0,0,0,0,0,0,0,0,0,0,0,0,0,0,0,0,0,0,0,0,0,0,0,0,0,0,0,0,0,0,0,0,0,0,0,0,0,0,0,0,0,0,0,0,0,0,0,0,0,0,0,0,0,0,0,0,0,0,0,0,0,0,0,0,0,0,0,0,0,0,0,0,0,0,0,0,0,0,0,0,0,0,0,0,0,0,0,0,0,0,0,0,0,0,0,0,0,0,0,0,0,0,0,0,0,0,0,0,0,0,0,0,0,0,0,0,0,0,0,0,0,0,0,0,0,0,0,0,0,0,0,0,0,0,0,0,0,0,0],"height":13,"id":48,"name":"Wall ","opacity":1,"type":"tilelayer","visible":true,"width":21,"x":0,"y":0},{"data":[0,0,0,0,0,0,0,0,0,0,0,0,0,0,0,0,0,0,0,0,0,0,0,0,0,0,0,0,0,0,0,0,0,0,0,0,0,0,0,0,0,0,0,0,0,0,0,0,0,0,0,0,0,0,0,0,0,0,0,0,0,0,0,0,0,0,0,0,0,0,0,0,0,0,0,0,0,0,0,0,0,0,0,0,0,0,0,0,0,0,0,0,0,0,0,0,0,0,0,0,0,0,0,0,0,0,0,0,0,0,0,0,0,0,0,0,0,0,0,0,0,0,0,0,0,0,0,0,0,0,0,0,0,0,0,0,0,0,0,0,0,0,0,0,0,0,0,0,0,0,0,0,0,0,0,0,0,0,0,0,0,0,0,0,0,0,0,0,0,0,0,0,0,0,0,0,0,0,0,0,0,0,0,0,0,0,0,0,0,0,0,0,0,0,0,0,0,0,0,0,0,0,0,0,0,0,0,0,0,0,0,0,0,0,0,0,0,0,0,0,0,0,0,0,0,0,0,0,0,0,0,0,0,0,0,0,0,0,0,0,0,0,0,0,0,0,0,0,0,0,0,0,0,0,0,0,0,0,0,0,0,0,0,0,0,0,0,0,0,0,0,0,0],"height":13,"id":49,"name":"Wall 1","opacity":1,"type":"tilelayer","visible":true,"width":21,"x":0,"y":0},{"data":[2701,2702,2702,2702,2702,2702,2702,2702,2702,2702,2702,2702,2702,2702,2702,2702,2702,2702,2702,2702,2703,2781,2782,2782,2782,2782,2782,2782,2782,2782,2782,2782,2782,2782,2782,2782,2782,2782,2782,2782,2782,2783,2861,2862,2862,2862,2862,2862,2862,2862,2862,2862,2862,2862,2862,2862,2862,2862,2862,2862,2862,2862,2863,0,0,0,0,0,0,0,0,0,0,0,0,0,0,0,0,0,0,0,0,0,0,0,0,0,0,0,0,0,0,0,0,0,0,0,0,0,0,0,0,0,0,0,0,0,0,0,0,0,0,0,0,0,0,0,0,0,0,0,0,0,0,0,0,0,0,0,0,0,0,0,0,0,0,0,0,0,0,0,0,0,0,0,0,0,0,0,0,0,0,0,0,0,0,0,0,0,0,0,0,0,0,0,0,0,0,0,0,0,0,0,0,0,0,0,0,0,0,0,0,0,0,0,0,0,0,0,0,0,0,0,0,0,0,0,0,0,0,0,0,0,0,0,0,0,0,0,0,0,0,0,0,0,0,0,0,0,0,0,0,0,0,0,0,0,0,0,0,0,0,0,0,0,0,0,0,0,0,0,0,0,0,0,0,0,0,0,0,0,0,0,0,0,0,0,0,0,0,0,0,0,0,0,0,0,0,0,0,0,0],"height":13,"id":50,"name":"Wall 2","opacity":1,"type":"tilelayer","visible":true,"width":21,"x":0,"y":0},{"data":[0,0,0,0,0,0,3901,3902,0,0,3585,3586,3587,0,0,3901,3902,0,0,0,0,0,0,0,0,0,0,3981,3982,0,0,3665,3666,3667,0,0,3981,3982,0,0,0,0,0,0,0,0,0,0,4061,4062,0,0,3745,17642,3747,0,0,4061,4062,0,0,0,0,0,0,0,0,0,0,0,0,0,0,3825,17708,3827,0,0,0,0,0,0,0,0,0,0,0,0,0,0,0,0,0,0,0,0,0,0,0,0,0,0,0,0,0,0,0,0,0,0,0,0,0,0,0,0,0,0,0,0,0,0,0,0,0,0,0,0,0,0,0,0,0,0,0,0,0,0,0,0,0,0,0,0,0,0,0,0,0,0,0,0,0,0,0,0,0,0,0,0,0,0,0,0,0,0,0,0,0,0,0,0,0,0,0,0,0,0,0,0,0,0,0,0,0,0,0,0,0,0,0,0,0,0,0,0,0,0,0,0,0,0,0,0,0,0,0,0,0,0,0,0,0,0,0,0,0,0,0,0,0,0,0,0,0,0,0,0,0,0,0,0,0,0,0,0,0,0,0,0,0,0,0,0,0,0,0,0,0,0,0,0,0,0,0,0,0,0,0,0,0,0,0,0,0,0,0,0,0,0,0,0,0],"height":13,"id":51,"name":"Wall 3","opacity":1,"type":"tilelayer","visible":true,"width":21,"x":0,"y":0},{"data":[0,0,0,0,0,0,0,0,0,0,0,0,0,0,0,0,0,0,0,0,0,0,0,0,0,0,0,0,0,0,0,0,0,0,0,0,0,0,0,0,0,0,0,0,0,0,0,0,0,0,0,0,0,0,0,0,0,0,0,0,0,0,0,0,0,0,0,0,0,0,0,0,0,0,0,0,0,0,0,0,0,0,0,0,0,0,0,0,0,0,0,0,0,0,0,0,0,0,0,0,0,0,0,0,0,0,0,0,0,0,0,0,0,0,0,0,0,0,0,0,0,0,0,0,0,0,0,0,0,0,0,0,0,0,0,0,0,0,0,0,0,0,0,0,0,0,0,0,0,0,0,0,0,0,0,0,0,0,0,0,0,0,0,0,0,0,0,0,0,0,0,0,0,0,0,0,0,0,0,0,0,0,0,0,0,0,0,0,0,0,0,0,0,0,0,0,0,0,0,0,0,0,0,0,0,0,0,0,0,0,0,0,0,0,0,0,0,0,0,0,0,0,0,0,0,0,0,0,0,0,0,0,0,0,0,0,0,0,0,0,0,0,0,0,0,0,0,0,0,0,0,0,0,0,0,0,0,0,0,0,0,0,0,0,0,0,0,0,0,0,0,0,0],"height":13,"id":52,"name":"Wall 4","opacity":1,"type":"tilelayer","visible":true,"width":21,"x":0,"y":0},{"data":[0,0,0,0,0,0,0,0,0,0,0,0,0,0,0,0,0,0,0,0,0,0,0,0,0,0,0,0,0,0,0,0,0,0,0,0,0,0,0,0,0,0,0,0,0,0,0,0,0,0,0,0,0,0,0,0,0,0,0,0,0,0,0,0,0,0,0,0,0,0,0,0,0,0,0,0,0,0,0,0,0,0,0,0,0,0,0,0,0,0,0,0,0,0,0,0,0,0,0,0,0,0,0,0,0,0,0,0,0,0,0,0,0,0,0,0,0,0,0,0,0,0,0,0,0,0,0,0,0,0,0,0,0,0,0,0,0,0,0,0,0,0,0,0,0,0,0,0,0,0,0,0,0,0,0,0,0,0,0,0,0,0,0,0,0,0,0,0,0,0,0,0,0,0,0,0,0,0,0,0,0,0,0,0,0,0,0,0,0,0,0,0,0,0,0,0,0,0,0,0,0,0,0,0,0,0,0,0,0,0,0,0,0,0,0,0,0,0,0,0,0,0,0,0,0,0,0,0,0,0,0,0,0,0,0,0,0,0,0,0,0,0,0,0,0,0,0,0,0,0,0,0,0,0,0,0,0,0,0,0,0,0,0,0,0,0,0,0,0,0,0,0,0],"height":13,"id":53,"name":"Wall 5","opacity":1,"type":"tilelayer","visible":true,"width":21,"x":0,"y":0}],"name":"Wall","opacity":1,"type":"group","visible":true,"x":0,"y":0},{"id":61,"layers":[{"data":[0,0,0,0,0,0,0,0,0,0,0,0,0,0,0,0,0,0,0,0,0,0,0,0,0,0,0,0,0,0,0,0,0,0,0,0,0,0,0,0,0,0,0,0,0,0,0,0,0,0,0,3308,0,0,0,0,0,0,0,0,0,0,0,0,0,0,0,0,0,0,0,0,3388,0,0,0,0,0,0,0,0,0,0,0,0,0,0,0,0,0,0,0,0,0,0,0,0,0,0,0,0,0,0,0,0,0,0,0,0,0,0,0,0,0,0,0,0,0,0,0,0,0,0,0,0,0,0,0,0,0,0,0,0,0,0,0,0,0,0,0,0,0,0,0,0,0,0,0,0,2147486951,2147486950,0,0,0,0,0,0,0,0,0,0,0,0,0,0,0,0,0,0,2147487032,2147487031,2147487030,2147487029,0,0,0,0,0,0,0,0,0,0,0,0,0,0,0,0,0,2147487112,2147487111,2147487110,2147487109,0,0,0,0,0,0,0,0,0,0,0,0,0,0,0,0,0,0,2147487191,2147487190,2147487189,0,0,0,0,0,0,0,0,0,0,0,0,0,0,0,0,0,0,0,0,0,0,0,0,0,0,0,0,0,0,0,0,0,0,0,0,0,0,0,0,0,0,0,0,0,0,0,0,0,0,0,0,0,0,0,0,0,0],"height":13,"id":55,"name":"Details","opacity":1,"type":"tilelayer","visible":true,"width":21,"x":0,"y":0},{"data":[0,0,0,0,0,0,0,0,0,0,0,0,0,0,0,0,0,0,0,0,0,0,0,0,0,0,2147491242,0,0,0,0,0,0,0,0,0,0,0,0,0,0,0,0,0,0,0,0,2147491322,0,0,0,0,0,0,0,0,2147491092,2147491091,2147491090,2147487116,0,0,0,2147491087,2147491086,2147491085,0,0,2147491402,0,0,0,0,0,0,0,0,2147491172,2147491171,2147491170,2147487196,0,0,0,2147491167,2147491166,2147491165,0,0,0,0,0,0,0,0,0,2147491089,0,2147490703,2147490702,2147490701,2147487276,2147491088,0,0,2147491247,2147491246,2147491245,0,0,0,0,0,0,0,0,0,2147491169,0,2147490783,2147490782,2147490781,0,2147491168,0,0,0,0,0,0,0,0,0,0,0,0,0,0,2147491249,0,2147490863,2147490862,2147490861,0,2147491248,0,0,0,0,0,0,0,0,0,0,0,0,0,0,0,0,0,0,0,0,0,0,0,0,0,0,0,0,0,0,0,0,0,0,0,0,0,2147491252,2147491251,2147491250,0,0,0,0,0,0,0,0,0,0,0,0,0,0,0,0,0,0,0,0,0,0,0,0,0,0,0,0,0,0,0,0,0,0,0,0,0,0,0,0,0,0,0,0,0,0,0,0,0,0,0,0,0,0,0,0,0,0,0,0,0,0,0,0,0,0,0,0,0,0,0,0,0,0,0,0,0,0,0,0,0,0,0,0,0,0,0,0],"height":13,"id":56,"name":"Details 1","opacity":1,"type":"tilelayer","visible":true,"width":21,"x":0,"y":0},{"data":[0,0,0,0,0,0,0,0,0,0,0,0,0,0,0,0,0,0,0,0,0,0,0,0,0,0,0,0,0,0,0,0,0,0,0,0,0,0,0,0,0,0,0,0,0,0,0,0,0,0,0,0,2147491824,0,0,0,0,0,0,0,0,0,0,0,0,0,0,0,0,0,0,0,0,2147491904,0,0,0,0,0,0,0,0,0,0,0,0,0,0,0,2147491089,0,0,0,0,2147491088,0,0,0,0,0,0,0,0,0,0,2147491241,0,0,0,0,2147491169,0,2147489886,2147489885,0,2147491168,0,0,0,2147491805,2147491806,2147491805,0,0,0,0,2147491321,0,0,0,0,2147491249,0,2147489966,2147489965,0,2147491248,0,0,0,0,0,0,0,0,0,0,2147491401,0,0,0,0,0,0,0,0,0,0,0,0,0,0,0,0,0,0,0,0,0,0,0,0,0,0,0,0,0,0,0,0,0,0,0,0,0,0,0,0,0,0,0,0,0,0,0,0,0,0,0,0,0,0,0,0,0,0,0,0,0,0,0,0,0,0,0,0,0,0,0,0,0,0,0,0,0,0,0,0,0,0,0,0,0,0,0,0,0,0,0,0,0,0,0,0,0,0,0,0,0,0,0,0,0,0,0,0,0,0,0,0,0,0,0,0,0,0,0,0,0,0,0,0,0],"height":13,"id":57,"name":"Details 2","opacity":1,"type":"tilelayer","visible":true,"width":21,"x":0,"y":0},{"data":[0,0,0,0,0,0,0,0,0,0,0,0,0,0,0,0,0,0,0,0,0,0,0,0,0,0,0,0,0,0,0,0,0,0,0,0,0,0,0,0,0,0,0,0,0,0,0,0,0,0,0,0,0,0,0,0,0,0,0,0,0,0,0,0,0,0,0,0,0,0,0,0,0,0,0,0,0,0,0,0,0,0,0,0,0,0,0,0,0,0,0,0,0,0,0,0,0,0,0,0,0,0,0,0,0,0,0,0,0,0,0,0,0,2147491810,0,0,0,0,0,0,0,0,0,0,0,0,0,0,0,0,0,0,0,0,0,0,0,0,0,0,0,0,0,0,0,0,0,0,0,0,0,0,0,0,0,0,0,0,0,0,0,0,0,0,0,0,0,0,0,0,0,0,0,0,0,0,0,0,0,0,0,0,0,0,0,0,0,0,0,0,0,0,0,0,0,0,0,0,0,0,0,0,0,0,0,0,0,0,0,0,0,0,0,0,0,0,0,0,0,0,0,0,0,0,0,0,0,0,0,0,0,0,0,0,0,0,0,0,0,0,0,0,0,0,0,0,0,0,0,0,0,0,0,0,0,0,0,0,0,0,0,0,0,0,0,0,0,0,0,0,0,0,0],"height":13,"id":58,"name":"Details 3","opacity":1,"type":"tilelayer","visible":true,"width":21,"x":0,"y":0},{"data":[0,0,0,0,0,0,0,0,0,0,0,0,0,0,0,0,0,0,0,0,0,0,0,0,0,0,0,0,0,0,0,0,0,0,0,0,0,0,0,0,0,0,0,0,0,0,0,0,0,0,0,0,0,0,0,0,0,0,0,0,0,0,0,0,0,0,0,0,0,0,0,0,0,0,0,0,0,0,0,0,0,0,0,0,0,0,0,0,0,0,0,0,0,0,0,0,0,0,0,0,0,0,0,0,0,0,0,0,0,0,0,0,0,0,0,0,0,0,0,0,0,0,0,0,0,0,0,0,0,0,0,0,0,0,0,0,0,0,0,0,0,0,0,0,0,0,0,0,0,0,0,0,0,0,0,0,0,0,0,0,0,0,0,0,0,0,0,0,0,0,0,0,0,0,0,0,0,0,0,0,0,0,0,0,0,0,0,0,0,0,0,0,0,0,0,0,0,0,0,0,0,0,0,0,0,0,0,0,0,0,0,0,0,0,0,0,0,0,0,0,0,0,0,0,0,0,0,0,0,0,0,0,0,0,0,0,0,0,0,0,0,0,0,0,0,0,0,0,0,0,0,0,0,0,0,0,0,0,0,0,0,0,0,0,0,0,0,0,0,0,0,0,0],"height":13,"id":59,"name":"Details 4","opacity":1,"type":"tilelayer","visible":true,"width":21,"x":0,"y":0},{"data":[0,0,0,0,0,0,0,0,0,0,0,0,0,0,0,0,0,0,0,0,0,0,0,0,0,0,0,0,0,0,0,0,0,0,0,0,0,0,0,0,0,0,0,0,0,0,0,0,0,0,0,0,0,0,0,0,0,0,0,0,0,0,0,0,0,0,0,0,0,0,0,0,0,0,0,0,0,0,0,0,0,0,0,0,0,0,0,0,0,0,0,0,0,0,0,0,0,0,0,0,0,0,0,0,0,0,0,0,0,0,0,0,0,0,0,0,0,0,0,0,0,0,0,0,0,0,0,0,0,0,0,0,0,0,0,0,0,0,0,0,0,0,0,0,0,0,0,0,0,0,0,0,0,0,0,0,0,0,0,0,0,0,0,0,0,0,0,0,0,0,0,0,0,0,0,0,0,0,0,0,0,0,0,0,0,0,0,0,0,0,0,0,0,0,0,0,0,0,0,0,0,0,0,0,0,0,0,0,0,0,0,0,0,0,0,0,0,0,0,0,0,0,0,0,0,0,0,0,0,0,0,0,0,0,0,0,0,0,0,0,0,0,0,0,0,0,0,0,0,0,0,0,0,0,0,0,0,0,0,0,0,0,0,0,0,0,0,0,0,0,0,0,0],"height":13,"id":60,"name":"Details 5","opacity":1,"type":"tilelayer","visible":true,"width":21,"x":0,"y":0}],"name":"Details","opacity":1,"type":"group","visible":true,"x":0,"y":0},{"draworder":"topdown","id":2,"name":"floorLayer","objects":[],"opacity":1,"type":"objectgroup","visible":true,"x":0,"y":0},{"id":68,"layers":[{"data":[0,0,0,0,0,0,0,0,0,0,0,0,0,0,0,0,0,0,0,0,0,0,0,0,0,0,0,0,0,0,0,0,0,0,0,0,0,0,0,0,0,0,0,0,0,0,0,0,0,0,0,0,0,0,0,0,0,0,0,0,0,0,0,0,0,0,0,0,0,0,0,0,0,0,0,0,0,0,0,0,0,0,0,0,0,0,0,0,0,0,0,0,0,0,0,0,0,0,0,0,0,0,0,0,0,0,0,0,0,0,0,0,0,0,0,0,0,0,0,0,0,0,0,0,0,0,0,0,0,0,0,0,0,0,0,0,0,0,0,0,0,0,0,0,0,0,0,0,0,0,0,0,0,0,0,0,0,0,0,0,0,0,0,0,0,0,0,0,0,0,0,0,0,0,0,0,0,0,0,0,0,0,0,0,0,0,0,0,0,0,0,0,0,0,0,0,0,0,0,0,0,0,0,0,0,0,0,0,0,0,0,0,0,0,0,0,0,0,0,0,0,0,0,0,0,0,0,0,0,0,0,0,0,0,0,0,0,0,0,0,0,0,0,0,0,0,0,0,0,0,0,0,0,0,0,0,0,0,0,0,0,0,0,0,0,0,0,0,0,0,0,0,0],"height":13,"id":62,"name":"Above","opacity":1,"type":"tilelayer","visible":false,"width":21,"x":0,"y":0},{"data":[0,0,0,0,0,0,0,0,0,0,0,0,0,0,0,0,0,0,0,0,0,0,0,0,0,0,0,0,0,0,0,0,0,0,0,0,0,0,0,0,0,0,0,0,0,0,0,0,0,0,0,0,0,0,0,0,0,0,0,0,0,0,0,0,0,0,0,0,0,0,0,0,0,0,0,0,0,0,0,0,0,0,0,0,0,0,0,0,0,0,0,0,0,0,0,0,0,0,0,0,0,0,0,0,0,0,0,0,0,0,0,0,0,0,0,0,0,0,0,0,0,0,0,0,0,0,0,0,0,0,0,0,0,0,0,0,0,0,0,0,0,0,0,0,0,0,0,0,0,0,0,0,0,0,0,0,0,0,0,0,0,0,0,0,0,0,0,0,0,0,0,0,0,0,0,0,0,0,0,0,0,0,0,0,0,0,0,0,0,0,0,0,0,0,0,0,0,0,0,0,0,0,0,0,0,0,0,0,0,0,0,0,0,0,0,0,0,0,0,0,0,0,0,0,0,0,0,0,0,0,0,0,0,0,0,0,0,0,0,0,0,0,0,0,0,0,0,0,0,0,0,0,0,0,0,0,0,0,0,0,0,0,0,0,0,0,0,0,0,0,0,0,0],"height":13,"id":63,"name":"Above 1","opacity":1,"type":"tilelayer","visible":true,"width":21,"x":0,"y":0},{"data":[0,0,0,0,0,0,0,0,0,0,0,0,0,0,0,0,0,0,0,0,0,0,0,0,0,0,0,0,0,0,0,0,0,0,0,0,0,0,0,0,0,0,0,0,0,0,0,0,0,0,0,0,0,0,0,0,0,0,0,0,0,0,0,0,0,0,0,0,0,0,0,0,0,0,0,0,0,0,0,0,0,0,0,0,0,0,0,0,0,0,0,0,0,0,0,0,0,0,0,0,0,0,0,0,0,0,0,0,0,0,0,0,0,0,0,0,0,0,0,0,0,0,0,0,0,0,0,0,0,0,0,0,0,0,0,0,0,0,0,0,0,0,0,0,0,0,0,0,0,0,0,0,0,0,0,0,0,0,0,0,0,0,0,0,0,0,0,0,0,0,0,0,0,0,0,0,0,0,0,0,0,0,0,0,0,0,0,0,0,0,0,0,0,0,0,0,0,0,0,0,0,0,0,0,0,0,0,0,0,0,0,0,0,0,0,0,0,0,0,0,0,0,0,0,0,0,0,0,0,0,0,0,0,0,0,0,0,0,0,0,0,0,0,0,0,0,0,0,0,0,0,0,0,0,0,0,0,0,0,0,0,0,0,0,0,0,0,0,0,0,0,0,0],"height":13,"id":64,"name":"Above 2","opacity":1,"type":"tilelayer","visible":true,"width":21,"x":0,"y":0},{"data":[0,0,0,0,0,0,0,0,0,0,0,0,0,0,0,0,0,0,0,0,0,0,0,0,0,0,0,0,0,0,0,0,0,0,0,0,0,0,0,0,0,0,0,0,0,0,0,0,0,0,0,0,0,0,0,0,0,0,0,0,0,0,0,0,0,0,0,0,0,0,0,0,0,0,0,0,0,0,0,0,0,0,0,0,0,0,0,0,0,0,0,0,0,0,0,0,0,0,0,0,0,0,0,0,0,0,0,0,0,0,0,0,0,0,0,0,0,0,0,0,0,0,0,0,0,0,0,0,0,0,0,0,0,0,0,0,0,0,0,0,0,0,0,0,0,0,0,0,0,0,0,0,0,0,0,0,0,0,0,0,0,0,0,0,0,0,0,0,0,0,0,0,0,0,0,0,0,0,0,0,0,0,0,0,0,0,0,0,0,0,0,0,0,0,0,0,0,0,0,0,0,0,0,0,0,0,0,0,0,0,0,0,0,0,0,0,0,0,0,0,0,0,0,0,0,0,0,0,0,0,0,0,0,0,0,0,0,0,0,0,0,0,0,0,0,0,0,0,0,0,0,0,0,0,0,0,0,0,0,0,0,0,0,0,0,0,0,0,0,0,0,0,0],"height":13,"id":65,"name":"Above 3","opacity":1,"type":"tilelayer","visible":true,"width":21,"x":0,"y":0},{"data":[0,0,0,0,0,0,0,0,0,0,0,0,0,0,0,0,0,0,0,0,0,0,0,0,0,0,0,0,0,0,0,0,0,0,0,0,0,0,0,0,0,0,0,0,0,0,0,0,0,0,0,0,0,0,0,0,0,0,0,0,0,0,0,0,0,0,0,0,0,0,0,0,0,0,0,0,0,0,0,0,0,0,0,0,0,0,0,0,0,0,0,0,0,0,0,0,0,0,0,0,0,0,0,0,0,0,0,0,0,0,0,0,0,0,0,0,0,0,0,0,0,0,0,0,0,0,0,0,0,0,0,0,0,0,0,0,0,0,0,0,0,0,0,0,0,0,0,0,0,0,0,0,0,0,0,0,0,0,0,0,0,0,0,0,0,0,0,0,0,0,0,0,0,0,0,0,0,0,0,0,0,0,0,0,0,0,0,0,0,0,0,0,0,0,0,0,0,0,0,0,0,0,0,0,0,0,0,0,0,0,0,0,0,0,0,0,0,0,0,0,0,0,0,0,0,0,0,0,0,0,0,0,0,0,0,0,0,0,0,0,0,0,0,0,0,0,0,0,0,0,0,0,0,0,0,0,0,0,0,0,0,0,0,0,0,0,0,0,0,0,0,0,0],"height":13,"id":66,"name":"Above 4","opacity":1,"type":"tilelayer","visible":true,"width":21,"x":0,"y":0},{"data":[0,0,0,0,0,0,0,0,0,0,0,0,0,0,0,0,0,0,0,0,0,0,0,0,0,0,0,0,0,0,0,0,0,0,0,0,0,0,0,0,0,0,0,0,0,0,0,0,0,0,0,0,0,0,0,0,0,0,0,0,0,0,0,0,0,0,0,0,0,0,0,0,0,0,0,0,0,0,0,0,0,0,0,0,0,0,0,0,0,0,0,0,0,0,0,0,0,0,0,0,0,0,0,0,0,0,0,0,0,0,0,0,0,0,0,0,0,0,0,0,0,0,0,0,0,0,0,0,0,0,0,0,0,0,0,0,0,0,0,0,0,0,0,0,0,0,0,0,0,0,0,0,0,0,0,0,0,0,0,0,0,0,0,0,0,0,0,0,0,0,0,0,0,0,0,0,0,0,0,0,0,0,0,0,0,0,0,0,0,0,0,0,0,0,0,0,0,0,0,0,0,0,0,0,0,0,0,0,0,0,0,0,0,0,0,0,0,0,0,0,0,0,0,0,0,0,0,0,0,0,0,0,0,0,0,0,0,0,0,0,0,0,0,0,0,0,0,0,0,0,0,0,0,0,0,0,0,0,0,0,0,0,0,0,0,0,0,0,0,0,0,0,0],"height":13,"id":67,"name":"Above 5","opacity":1,"type":"tilelayer","visible":true,"width":21,"x":0,"y":0},{"data":[0,0,0,0,0,0,0,0,0,0,0,0,0,0,0,0,0,0,0,0,0,0,0,0,0,0,0,0,0,0,0,0,0,0,0,0,0,0,0,0,0,0,0,0,0,0,0,0,0,0,0,0,0,0,0,0,0,0,0,0,0,0,0,0,0,0,0,0,0,0,0,0,0,0,0,0,0,0,0,0,0,0,0,0,0,0,0,0,0,0,0,0,0,0,0,0,0,0,0,0,0,0,0,0,0,0,0,0,0,0,0,0,0,0,0,0,0,7283,0,0,0,0,0,0,0,0,0,0,0,0,0,0,0,0,0,0,0,0,7363,0,0,0,0,0,0,0,0,0,0,0,0,0,0,0,0,0,0,0,0,0,0,0,0,0,0,0,0,0,0,0,0,0,0,0,0,0,0,0,0,0,0,0,0,0,0,0,0,0,0,0,0,0,0,0,0,0,0,0,0,0,0,0,0,0,0,0,0,0,0,0,0,0,0,0,0,0,0,0,0,0,0,0,0,0,0,0,0,0,0,0,0,0,23095,23096,23097,23098,0,0,0,0,0,0,0,0,0,0,0,0,0,0,0,0,0,23116,23117,23118,23119,0,0,0,0,0,0,0,0,0,0,0,0,0,0,0,0],"height":13,"id":82,"name":"Above 6","opacity":1,"type":"tilelayer","visible":true,"width":21,"x":0,"y":0}],"name":"Above","opacity":1,"type":"group","visible":true,"x":0,"y":0}],"nextlayerid":98,"nextobjectid":10,"orientation":"orthogonal","properties":[{"name":"mapCopyright","type":"string","value":"Credits: WorkAdventure \n https://workadventu.re"},{"name":"mapDescription","type":"string","value":"Map for dev event of SOGETI"},{"name":"mapImage","type":"string","value":"secretroom.png"},{"name":"mapLink","type":"string","value":"TODO"},{"name":"mapName","type":"string","value":"SecretRoom"},{"name":"script","type":"string","value":"script.js"}],"renderorder":"right-down","tiledversion":"1.7.2","tileheight":32,"tilesets":[{"columns":6,"firstgid":1,"image":"src/assets/Special_Zones.png","imageheight":68,"imagewidth":204,"margin":1,"name":"Special_Zones","properties":[{"name":"tilesetCopyright","type":"string","value":"© 2021 WorkAdventure <https://workadventu.re/> \nLicense: WORKADVENTURE SPECIFIC RESOURCES LICENSE (see LICENSE.assets file)"}],"spacing":2,"tilecount":12,"tileheight":32,"tiles":[{"id":0,"properties":[{"name":"collides","type":"bool","value":true}]}],"tilewidth":32},{"columns":40,"firstgid":13,"image":"src/assets/Deco abcf 1.png","imageheight":1598,"imagewidth":1360,"margin":1,"name":"Deco abcf 1","spacing":2,"tilecount":1880,"tileheight":32,"tilewidth":32},{"columns":40,"firstgid":1893,"image":"src/assets/Deco abcf 2.png","imageheight":646,"imagewidth":1360,"margin":1,"name":"Deco abcf 2","spacing":2,"tilecount":760,"tileheight":32,"tilewidth":32},{"columns":80,"firstgid":2653,"image":"src/assets/Deco e 1.png","imageheight":2448,"imagewidth":2720,"margin":1,"name":"Deco e 1","spacing":2,"tilecount":5760,"tileheight":32,"tilewidth":32},{"columns":28,"firstgid":8413,"image":"src/assets/Floor and water 1.png","imageheight":1020,"imagewidth":952,"margin":1,"name":"Floor and water 1","spacing":2,"tilecount":840,"tileheight":32,"tiles":[{"animation":[{"duration":250,"tileid":620},{"duration":250,"tileid":621},{"duration":250,"tileid":622}],"id":620},{"animation":[{"duration":250,"tileid":622},{"duration":250,"tileid":620},{"duration":250,"tileid":621}],"id":622},{"animation":[{"duration":250,"tileid":649},{"duration":250,"tileid":650},{"duration":250,"tileid":676},{"duration":250,"tileid":677},{"duration":250,"tileid":678},{"duration":250,"tileid":648}],"id":649}],"tilewidth":32},{"columns":30,"firstgid":9253,"image":"src/assets/Floor and water 2.png","imageheight":1020,"imagewidth":1020,"margin":1,"name":"Floor and water 2","spacing":2,"tilecount":900,"tileheight":32,"tilewidth":32},{"columns":64,"firstgid":10153,"image":"src/assets/Houses be.png","imageheight":2278,"imagewidth":2176,"margin":1,"name":"Houses be","spacing":2,"tilecount":4288,"tileheight":32,"tilewidth":32},{"columns":40,"firstgid":14441,"image":"src/assets/Moutains b.png","imageheight":1632,"imagewidth":1360,"margin":1,"name":"Moutains b","spacing":2,"tilecount":1920,"tileheight":32,"tilewidth":32},{"columns":20,"firstgid":16361,"image":"src/assets/Smoke VFX3.png","imageheight":34,"imagewidth":680,"margin":1,"name":"Smoke VFX3","spacing":2,"tilecount":20,"tileheight":32,"tilewidth":32},{"columns":40,"firstgid":16381,"image":"src/assets/Trees and flowers.png","imageheight":952,"imagewidth":1360,"margin":1,"name":"Trees and flowers","spacing":2,"tilecount":1120,"tileheight":32,"tilewidth":32},{"columns":66,"firstgid":17501,"image":"src/assets/Windows.png","imageheight":1632,"imagewidth":2244,"margin":1,"name":"Windows","spacing":2,"tilecount":3168,"tileheight":32,"tiles":[{"animation":[{"duration":150,"tileid":141},{"duration":150,"tileid":142},{"duration":150,"tileid":143}],"id":141},{"animation":[{"duration":150,"tileid":207},{"duration":150,"tileid":208},{"duration":150,"tileid":209}],"id":207},{"animation":[{"duration":100,"tileid":831},{"duration":100,"tileid":897},{"duration":100,"tileid":963},{"duration":100,"tileid":1029}],"id":831},{"animation":[{"duration":100,"tileid":1368},{"duration":100,"tileid":1632},{"duration":100,"tileid":1896},{"duration":100,"tileid":2160}],"id":1368},{"animation":[{"duration":100,"tileid":1369},{"duration":100,"tileid":1633},{"duration":100,"tileid":1897},{"duration":100,"tileid":2161}],"id":1369},{"animation":[{"duration":100,"tileid":1370},{"duration":100,"tileid":1634},{"duration":100,"tileid":1898},{"duration":100,"tileid":2162}],"id":1370},{"animation":[{"duration":100,"tileid":1434},{"duration":100,"tileid":1698},{"duration":100,"tileid":1962},{"duration":100,"tileid":2226}],"id":1434},{"animation":[{"duration":100,"tileid":1435},{"duration":100,"tileid":1699},{"duration":100,"tileid":1963},{"duration":100,"tileid":2227}],"id":1435},{"animation":[{"duration":100,"tileid":1436},{"duration":100,"tileid":1700},{"duration":100,"tileid":1964},{"duration":100,"tileid":2228}],"id":1436},{"animation":[{"duration":100,"tileid":1500},{"duration":100,"tileid":1764},{"duration":100,"tileid":2028},{"duration":100,"tileid":2292}],"id":1500},{"animation":[{"duration":100,"tileid":1501},{"duration":100,"tileid":1765},{"duration":100,"tileid":2029},{"duration":100,"tileid":2293}],"id":1501},{"animation":[{"duration":100,"tileid":1502},{"duration":100,"tileid":1766},{"duration":100,"tileid":2030},{"duration":100,"tileid":2294}],"id":1502},{"animation":[{"duration":100,"tileid":1566},{"duration":100,"tileid":1830},{"duration":100,"tileid":2094},{"duration":100,"tileid":2358}],"id":1566},{"animation":[{"duration":100,"tileid":1567},{"duration":100,"tileid":1831},{"duration":100,"tileid":2095},{"duration":100,"tileid":2359}],"id":1567},{"animation":[{"duration":100,"tileid":1568},{"duration":100,"tileid":1832},{"duration":100,"tileid":2096},{"duration":100,"tileid":2360}],"id":1568}],"tilewidth":32},{"columns":8,"firstgid":20669,"image":"src/assets/kitchen.png","imageheight":306,"imagewidth":272,"margin":1,"name":"kitchen","spacing":2,"tilecount":72,"tileheight":32,"tilewidth":32},{"columns":21,"firstgid":20741,"image":"src/assets/terrain.png","imageheight":782,"imagewidth":714,"margin":1,"name":"terrain","spacing":2,"tilecount":483,"tileheight":32,"tilewidth":32},{"columns":28,"firstgid":21224,"image":"src/assets/bar.png","imageheight":912,"imagewidth":912,"margin":0,"name":"bar","spacing":0,"tilecount":784,"tileheight":32,"tilewidth":32},{"columns":24,"firstgid":22008,"image":"src/assets/Inside_f.png","imageheight":816,"imagewidth":816,"margin":1,"name":"Inside_f","spacing":2,"tilecount":576,"tileheight":32,"tilewidth":32},{"columns":16,"firstgid":22584,"image":"src/assets/Celiana-interiors-1.png","imageheight":544,"imagewidth":544,"margin":1,"name":"Celiana-interiors-1","spacing":2,"tilecount":256,"tileheight":32,"tilewidth":32},{"columns":21,"firstgid":22840,"image":"src/typo.png","imageheight":680,"imagewidth":714,"margin":1,"name":"typo","spacing":2,"tilecount":420,"tileheight":32,"tilewidth":32},{"columns":6,"firstgid":23260,"image":"src/arrow-animation.png","imageheight":34,"imagewidth":204,"margin":1,"name":"arrow-animation","spacing":2,"tilecount":6,"tileheight":32,"tiles":[{"animation":[{"duration":150,"tileid":0},{"duration":150,"tileid":1},{"duration":150,"tileid":2},{"duration":150,"tileid":3},{"duration":150,"tileid":4},{"duration":150,"tileid":5}],"id":0}],"tilewidth":32},{"columns":8,"firstgid":23266,"image":"src/bubble-animation.png","imageheight":68,"imagewidth":272,"margin":1,"name":"bubble-animation","spacing":2,"tilecount":16,"tileheight":32,"tiles":[{"animation":[{"duration":150,"tileid":0},{"duration":150,"tileid":1},{"duration":150,"tileid":2},{"duration":150,"tileid":3},{"duration":150,"tileid":4},{"duration":150,"tileid":5},{"duration":150,"tileid":6},{"duration":150,"tileid":7}],"id":0},{"animation":[{"duration":150,"tileid":8},{"duration":150,"tileid":9},{"duration":150,"tileid":10},{"duration":150,"tileid":11},{"duration":150,"tileid":12},{"duration":150,"tileid":13},{"duration":150,"tileid":14},{"duration":150,"tileid":15}],"id":8}],"tilewidth":32}],"tilewidth":32,"type":"map","version":"1.6","width":21}